{
  "__id__": "ExperimentList", 
  "experiment": [
    {
      "__id__": "Experiment", 
      "identifier": "", 
      "beam": 0, 
      "detector": 0, 
      "goniometer": 0, 
      "scan": 0, 
      "crystal": 0, 
      "imageset": 0
    }
  ], 
  "imageset": [
    {
      "__id__": "ImageSweep", 
      "template": "/Users/atakisi/MLFSOM/distl/trial/myfake_###.img", 
      "mask": "", 
      "gain": "", 
      "pedestal": "", 
      "dx": "", 
      "dy": "", 
      "params": {
        "dynamic_shadowing": "Auto", 
        "multi_panel": false
      }
    }
  ], 
  "beam": [
    {
      "direction": [
        -0.029777220091573447, 
        0.0, 
        0.9995565602624086
      ], 
      "transmission": 1.0, 
      "polarization_normal": [
        0.0, 
        1.0, 
        0.0
      ], 
      "divergence": 0.0, 
      "polarization_fraction": 0.999, 
      "flux": 0.0, 
      "sigma_divergence": 0.0, 
      "wavelength": 1.0000000000000002
    }
  ], 
  "detector": [
    {
      "hierarchy": {
        "origin": [
          0.0, 
          0.0, 
          0.0
        ], 
        "fast_axis": [
          1.0, 
          0.0, 
          0.0
        ], 
        "name": "", 
        "raw_image_offset": [
          0, 
          0
        ], 
        "slow_axis": [
          0.0, 
          1.0, 
          0.0
        ], 
        "material": "", 
        "mask": [], 
        "thickness": 0.0, 
        "mu": 0.0, 
        "gain": 1.0, 
        "trusted_range": [
          0.0, 
          0.0
        ], 
        "image_size": [
          0, 
          0
        ], 
        "px_mm_strategy": {
          "type": "SimplePxMmStrategy"
        }, 
        "pedestal": 0.0, 
        "identifier": "", 
        "type": "", 
        "children": [
          {
            "panel": 0
          }
        ], 
        "pixel_size": [
          0.0, 
          0.0
        ]
      }, 
      "panels": [
        {
          "origin": [
            -216.79259013609894, 
            217.25441567081103, 
            -232.36739949948466
          ], 
          "fast_axis": [
            0.9999935375190695, 
            0.0001939842390108374, 
            0.003589887214443386
          ], 
          "name": "Panel", 
          "raw_image_offset": [
            0, 
            0
          ], 
          "slow_axis": [
            0.00022750704543327046, 
            -0.9999563547015577, 
            -0.009340071333604255
          ], 
          "material": "", 
          "mask": [], 
          "thickness": 0.0, 
          "mu": 0.0, 
          "gain": 1.0, 
          "trusted_range": [
            0.0, 
            65535.0
          ], 
          "image_size": [
            2463, 
            2527
          ], 
          "px_mm_strategy": {
            "type": "SimplePxMmStrategy"
          }, 
          "pedestal": 0.0, 
          "identifier": "", 
          "type": "SENSOR_CCD", 
          "pixel_size": [
            0.172, 
            0.172
          ]
        }
      ]
    }
  ], 
  "goniometer": [
    {
      "setting_rotation": [
        1.0, 
        0.0, 
        0.0, 
        0.0, 
        1.0, 
        0.0, 
        0.0, 
        0.0, 
        1.0
      ], 
      "fixed_rotation": [
        1.0, 
        0.0, 
        0.0, 
        0.0, 
        1.0, 
        0.0, 
        0.0, 
        0.0, 
        1.0
      ], 
      "rotation_axis": [
        1.0, 
        0.0, 
        0.0
      ]
    }
  ], 
  "scan": [
    {
      "exposure_time": [
        0.5, 
        0.5, 
        0.5, 
        0.5, 
        0.5, 
        0.5, 
        0.5, 
        0.5, 
        0.5, 
        0.5, 
        0.5, 
        0.5, 
        0.5, 
        0.5, 
        0.5, 
        0.5, 
        0.5, 
        0.5, 
        0.5, 
        0.5, 
        0.5, 
        0.5, 
        0.5, 
        0.5, 
        0.5, 
        0.5, 
        0.5, 
        0.5, 
        0.5, 
        0.5, 
        0.5, 
        0.5, 
        0.5, 
        0.5, 
        0.5, 
        0.5, 
        0.5, 
        0.5, 
        0.5, 
        0.5, 
        0.5, 
        0.5, 
        0.5, 
        0.5, 
        0.5, 
        0.5, 
        0.5, 
        0.5, 
        0.5, 
        0.5, 
        0.5, 
        0.5, 
        0.5, 
        0.5, 
        0.5, 
        0.5, 
        0.5, 
        0.5, 
        0.5, 
        0.5, 
        0.5, 
        0.5, 
        0.5, 
        0.5, 
        0.5, 
        0.5, 
        0.5, 
        0.5, 
        0.5, 
        0.5, 
        0.5, 
        0.5, 
        0.5, 
        0.5, 
        0.5, 
        0.5, 
        0.5, 
        0.5, 
        0.5, 
        0.5, 
        0.5, 
        0.5, 
        0.5, 
        0.5, 
        0.5, 
        0.5, 
        0.5, 
        0.5, 
        0.5, 
        0.5, 
        0.5, 
        0.5, 
        0.5, 
        0.5, 
        0.5, 
        0.5, 
        0.5, 
        0.5, 
        0.5, 
        0.5
      ], 
      "batch_offset": 0, 
      "oscillation": [
        342.0, 
        1.0
      ], 
      "valid_image_ranges": {}, 
      "epochs": [
        1582557112.0, 
        1582557182.0, 
        1582557253.0, 
        1582557323.0, 
        1582557392.0, 
        1582557466.0, 
        1582557537.0, 
        1582557601.0, 
        1582557673.0, 
        1582557754.0, 
        1582557830.0, 
        1582557896.0, 
        1582557956.0, 
        1582558020.0, 
        1582558092.0, 
        1582558167.0, 
        1582558240.0, 
        1582558307.0, 
        1582558369.0, 
        1582558431.0, 
        1582558498.0, 
        1582558571.0, 
        1582558645.0, 
        1582558718.0, 
        1582558784.0, 
        1582558847.0, 
        1582558912.0, 
        1582558989.0, 
        1582559070.0, 
        1582559141.0, 
        1582559206.0, 
        1582559274.0, 
        1582559347.0, 
        1582559415.0, 
        1582559485.0, 
        1582559556.0, 
        1582559625.0, 
        1582559697.0, 
        1582559765.0, 
        1582559832.0, 
        1582559906.0, 
        1582559970.0, 
        1582560036.0, 
        1582560105.0, 
        1582560181.0, 
        1582560256.0, 
        1582560327.0, 
        1582560396.0, 
        1582560463.0, 
        1582560537.0, 
        1582560614.0, 
        1582560689.0, 
        1582560753.0, 
        1582560825.0, 
        1582560893.0, 
        1582560955.0, 
        1582561020.0, 
        1582561094.0, 
        1582561171.0, 
        1582561248.0, 
        1582561318.0, 
        1582561388.0, 
        1582561458.0, 
        1582561526.0, 
        1582561594.0, 
        1582561664.0, 
        1582561734.0, 
        1582561803.0, 
        1582561879.0, 
        1582561956.0, 
        1582562030.0, 
        1582562094.0, 
        1582562156.0, 
        1582562224.0, 
        1582562297.0, 
        1582562360.0, 
        1582562433.0, 
        1582562511.0, 
        1582562585.0, 
        1582562651.0, 
        1582562719.0, 
        1582562792.0, 
        1582562867.0, 
        1582562944.0, 
        1582563012.0, 
        1582563079.0, 
        1582563145.0, 
        1582563220.0, 
        1582563288.0, 
        1582563359.0, 
        1582563432.0, 
        1582563501.0, 
        1582563572.0, 
        1582563642.0, 
        1582563711.0, 
        1582563784.0, 
        1582563853.0, 
        1582563918.0, 
        1582563991.0, 
        1582564072.0
      ], 
      "image_range": [
        1, 
        100
      ]
    }
  ], 
  "crystal": [
    {
      "__id__": "crystal", 
      "real_space_a": [
        0.01729321433853847, 
        -74.25190778183494, 
        -0.5185758235862217
      ], 
      "real_space_b": [
        -0.053896203178606834, 
        0.5185631492726475, 
        -74.25189032369273
      ], 
      "real_space_c": [
        36.48030318726962, 
        0.00868074490856139, 
        -0.02641883337418307
      ], 
      "space_group_hall_symbol": " P 4nw 2abw", 
      "B_covariance": [
        3.715233632446632e-11, 
        -4.549848976060361e-27, 
        8.593428205691975e-27, 
        -1.4247023771174725e-27, 
        3.715233632446632e-11, 
        -8.593428205691975e-27, 
        -1.009374549899573e-26, 
        2.438904536287023e-27, 
        7.017066644582792e-11, 
        -4.549848976060362e-27, 
        5.5719579851361834e-43, 
        -1.0523914345803259e-42, 
        1.7447572058745376e-43, 
        -4.549848976060362e-27, 
        1.0523914345803259e-42, 
        1.2361273116753121e-42, 
        -2.9867966337898617e-43, 
        -8.593428205691974e-27, 
        8.593428205691974e-27, 
        -1.0523914345803257e-42, 
        2.029013087016999e-42, 
        -3.295372190140066e-43, 
        8.593428205691974e-27, 
        -2.029013087016999e-42, 
        -2.3613729410125555e-42, 
        5.539717362079255e-43, 
        1.6568149187420215e-26, 
        -1.4247023771174725e-27, 
        1.7447572058745378e-43, 
        -3.2953721901400664e-43, 
        5.463389558162151e-44, 
        -1.4247023771174725e-27, 
        3.2953721901400664e-43, 
        3.870707640253516e-43, 
        -9.352609914123945e-44, 
        -2.6908755997520534e-27, 
        3.715233632446632e-11, 
        -4.549848976060361e-27, 
        8.593428205691975e-27, 
        -1.4247023771174725e-27, 
        3.715233632446632e-11, 
        -8.593428205691975e-27, 
        -1.009374549899573e-26, 
        2.438904536287023e-27, 
        7.017066644582792e-11, 
        -8.593428205691974e-27, 
        1.0523914345803257e-42, 
        -2.029013087016999e-42, 
        3.295372190140066e-43, 
        -8.593428205691974e-27, 
        2.029013087016999e-42, 
        2.3613729410125555e-42, 
        -5.539717362079255e-43, 
        -1.6568149187420215e-26, 
        -1.0093745498995727e-26, 
        1.236127311675312e-42, 
        -2.3613729410125558e-42, 
        3.870707640253516e-43, 
        -1.0093745498995727e-26, 
        2.3613729410125558e-42, 
        2.7595248340240796e-42, 
        -6.560646218212247e-43, 
        -1.928207335091747e-26, 
        2.4389045362870226e-27, 
        -2.9867966337898613e-43, 
        5.539717362079255e-43, 
        -9.352609914123943e-44, 
        2.4389045362870226e-27, 
        -5.539717362079255e-43, 
        -6.560646218212248e-43, 
        1.625985176070191e-43, 
        4.523522509458418e-27, 
        7.017066644582792e-11, 
        -8.593428205691974e-27, 
        1.6568149187420218e-26, 
        -2.690875599752053e-27, 
        7.017066644582792e-11, 
        -1.6568149187420218e-26, 
        -1.928207335091747e-26, 
        4.523522509458418e-27, 
        1.3528920500960448e-10
      ]
    }
  ], 
  "profile": [], 
  "scaling_model": []
}